{
  "timestamp": "2026-01-08T17:46:26.661091+00:00",
  "value": {
    "package.json": "{\n  \"name\": \"mechanics-of-motherhood\",\n  \"version\": \"1.0.0\",\n  \"type\": \"module\",\n  \"license\": \"MIT\",\n  \"scripts\": {\n    \"dev\": \"vite\",\n    \"build\": \"npm run clean && npm run build:github && npm run build:ssr && npm run prerender && npm run ssg\",\n    \"build:prerender\": \"npm run prerender\",\n    \"build:static\": \"vite build && node scripts/inject-build-version.js\",\n    \"build:ssr\": \"vite build --ssr src/ssr-entry.tsx --outDir ../dist/server\",\n    \"build:with-data\": \"npm run fetch-data && npm run build:static\",\n    \"build:seo\": \"npm run generate:sitemap && npm run build\",\n    \"build:github\": \"npm run fetch-data && npm run generate:sitemap && npm run validate-data && npm run validate:seo && vite build && node scripts/inject-build-version.js\",\n    \"fetch-data\": \"node scripts/fetch-data.js\",\n    \"validate-data\": \"node scripts/validate-data.js\",\n    \"validate-data:fix\": \"node scripts/validate-data.js --fix-issues\",\n    \"validate:seo\": \"node scripts/validate-seo-assets.js\",\n    \"test-api\": \"node scripts/test-api.js\",\n    \"preview\": \"vite preview\",\n    \"preview:github\": \"vite preview --base=/MechanicsOfMotherhood/\",\n    \"check\": \"tsc\",\n    \"clean\": \"node scripts/clean.js\",\n    \"clean:all\": \"npm run clean && node -e \\\"const fs = require('fs'); try { fs.rmSync('node_modules', { recursive: true, force: true }); fs.rmSync('package-lock.json', { force: true }); console.log('Removed node_modules and package-lock.json. Run npm install to reinstall dependencies.'); } catch (e) { console.log('Failed to remove some files:', e.message); }\\\"\",\n    \"prepare-v4\": \"node scripts/prepare-v4-migration.js\",\n    \"tailwind:check\": \"npx tailwindcss --help\",\n    \"generate:sitemap\": \"node scripts/generate-sitemap.js\",\n    \"seo:build\": \"npm run generate:sitemap && npm run build\",\n    \"seo:validate\": \"echo 'SEO validation tools would run here - check lighthouse, structured data testing, etc.'\",\n    \"deploy:check\": \"npm run check && npm run validate-data && npm run build:github && npm run preview:github\",\n    \"prerender\": \"node scripts/prerender.js\",\n    \"ssg\": \"tsx scripts/ssg.ts\",\n    \"analyze\": \"vite build --mode production && npx rollup-plugin-visualizer --json stats.json --template treemap --sourcemap false || true\",\n    \"test\": \"vitest run\",\n    \"test:watch\": \"vitest\",\n    \"test:ui\": \"vitest --ui\",\n    \"test:coverage\": \"vitest run --coverage\"\n  },\n  \"dependencies\": {\n    \"@radix-ui/react-dialog\": \"^1.1.15\",\n    \"@radix-ui/react-separator\": \"^1.1.8\",\n    \"@radix-ui/react-slot\": \"^1.2.4\",\n    \"@radix-ui/react-toast\": \"^1.2.15\",\n    \"@radix-ui/react-tooltip\": \"^1.2.8\",\n    \"@tailwindcss/typography\": \"^0.5.19\",\n    \"@tailwindcss/vite\": \"^4.1.18\",\n    \"class-variance-authority\": \"^0.7.1\",\n    \"clsx\": \"^2.1.1\",\n    \"dotenv\": \"^17.2.3\",\n    \"lucide-react\": \"^0.562.0\",\n    \"react\": \"^19.2.3\",\n    \"react-dom\": \"^19.2.3\",\n    \"react-helmet-async\": \"^2.0.5\",\n    \"react-markdown\": \"^10.1.0\",\n    \"tailwind-merge\": \"^3.4.0\",\n    \"tailwindcss\": \"^4.1.18\",\n    \"tailwindcss-animate\": \"^1.0.7\",\n    \"web-vitals\": \"^5.1.0\",\n    \"wouter\": \"^3.9.0\"\n  },\n  \"devDependencies\": {\n    \"@testing-library/dom\": \"^10.4.1\",\n    \"@testing-library/jest-dom\": \"^6.9.1\",\n    \"@testing-library/react\": \"^16.3.1\",\n    \"@testing-library/user-event\": \"^14.6.1\",\n    \"@types/node\": \"^25.0.3\",\n    \"@types/react\": \"^19.2.7\",\n    \"@types/react-dom\": \"^19.2.3\",\n    \"@vitejs/plugin-react\": \"^5.1.2\",\n    \"@vitest/coverage-v8\": \"^4.0.16\",\n    \"esbuild-register\": \"^3.6.0\",\n    \"glob\": \"^13.0.0\",\n    \"jsdom\": \"^27.4.0\",\n    \"fast-xml-parser\": \"^5.3.3\",\n    \"rollup-plugin-visualizer\": \"^6.0.5\",\n    \"tsx\": \"^4.21.0\",\n    \"typescript\": \"5.9.3\",\n    \"vite\": \"^7.3.0\",\n    \"vitest\": \"^4.0.16\"\n  }\n}\n"
  },
  "hash": "70c8eaa622c2b8c244bd470bde30ec1433bbb5bfea4e6859409aeba26b681c52",
  "metadata": {
    "repository": {
      "owner": "markhazleton",
      "name": "MechanicsOfMotherhood"
    },
    "category": "dependency_files",
    "pushed_at": "2026-01-04T18:02:36+00:00",
    "ttl_enforced": false
  },
  "category": "dependency_files",
  "owner": "markhazleton",
  "repo": "MechanicsOfMotherhood",
  "week": "2026-01-04T18-02-36+00-00"
}